auv/infer.py
auv/model.py
auv/modules/codec.py
auv/modules/conformer.py
auv/modules/factorized_vector_quantize.py
auv/modules/residual_vq.py
auv/modules/stft.py
auv-0.1.1.dist-info/licenses/LICENSE
auv-0.1.1.dist-info/METADATA
auv-0.1.1.dist-info/WHEEL
auv-0.1.1.dist-info/entry_points.txt
auv-0.1.1.dist-info/top_level.txt
auv-0.1.1.dist-info/RECORD
