Metadata-Version: 2.4
Name: auv
Version: 0.1.1
Summary: AUV: Teaching Audio Universal Vector Quantization with Single Nested Codebook
License: MIT License
Project-URL: Homepage, https://github.com/SWivid/AUV
Classifier: License :: OSI Approved :: MIT License
Classifier: Operating System :: OS Independent
Classifier: Programming Language :: Python :: 3
License-File: LICENSE
Requires-Dist: einops
Requires-Dist: torch>=2.0.0
Requires-Dist: torchaudio>=2.0.0
Dynamic: license-file
